tu32/__init__.py
tu32-1.0.dist-info/METADATA
tu32-1.0.dist-info/WHEEL
tu32-1.0.dist-info/top_level.txt
tu32-1.0.dist-info/RECORD
