Metadata-Version: 2.1
Name: tu32
Version: 1.0
Summary: 123
Home-page: UNKNOWN
Author: qdzzzxc
Author-email: 
License: UNKNOWN
Platform: UNKNOWN
Classifier: Programming Language :: Python :: 3
Classifier: License :: OSI Approved :: MIT License
Classifier: Operating System :: OS Independent
Requires-Python: >=3.6
